atri/__init__.py
atri/cli.py
atri/errors.py
atri/find_app_root.py
atri/stats.py
atri/commands/__init__.py
atri/commands/build_ssg_cmd.py
atri/commands/check_requisite.py
atri/commands/connect_local.py
atri/commands/create_dockerfile.py
atri/commands/deploy_ssg_gh_pages.py
atri/commands/load_exe.py
atri/commands/open_editor.py
atri/commands/open_exe.py
atri/utils/__init__.py
atri/utils/atri_dir_utils.py
atri/utils/call_compute.py
atri/utils/call_serve.py
atri/utils/conda_utils.py
atri/utils/globals.py
atri/utils/handle_error.py
atri/utils/in_venv.py
atri/utils/install_package.py
atri/utils/is_pkg_installed.py
atri/utils/manage_session.py
atri/utils/pipenv_utils.py
atri/utils/printd.py
atri/utils/run_shell_cmd.py
atri/utils/setup_env.py
atri/utils/wait_till_file_server_ready.py
atri-0.0.90.dist-info/METADATA
atri-0.0.90.dist-info/WHEEL
atri-0.0.90.dist-info/entry_points.txt
atri-0.0.90.dist-info/top_level.txt
atri-0.0.90.dist-info/RECORD
