Metadata-Version: 2.1
Name: atri
Version: 0.0.90
Summary: The best tools to build better and fast apps
Home-page: https://atrilabs.com
Author: Atri Labs
Author-email: shyam.swaroop@atrilabs.com
License: GPLv3
Project-URL: Source, https://github.com/cruxcode/atrilabs-engine.git
Requires-Python: >=3.7
Requires-Dist: click
Requires-Dist: python-socketio[asyncio_client]
Requires-Dist: toml
Requires-Dist: questionary
Requires-Dist: requests
Requires-Dist: pymongo[srv]
